Verilog/full_ckt.v
    module clad(a, b, cin, cout, s, clk);
    input [3:0] a, b;
    input cin, clk;     
    output [3:0] s;
    output cout; 

    wire p0, p1, p2, p3;
    wire g0, g1, g2, g3;
    wire e0, e1, e2, e3;
    wire c1, c2, c3;
    wire coutm, cinm;
    wire [3:0] am, bm, sm;

    // dff for 4bit a
    dff Da0(.Q(am[0]), .D(a[0]), .clk(clk));
    dff Da1(.Q(am[1]), .D(a[1]), .clk(clk));
    dff Da2(.Q(am[2]), .D(a[2]), .clk(clk));
    dff Da3(.Q(am[3]), .D(a[3]), .clk(clk));


    // dff for 4bit b
    dff Db0(.Q(bm[0]), .D(b[0]), .clk(clk));
    dff Db1(.Q(bm[1]), .D(b[1]), .clk(clk));
    dff Db2(.Q(bm[2]), .D(b[2]), .clk(clk));
    dff Db3(.Q(bm[3]), .D(b[3]), .clk(clk));
    
    // dff for cin
    dff Dcin(.Q(cinm), .D(cin), .clk(clk));

    // adder
    cla C1(.a(am), .b(bm), .cin(cinm), .cout(coutm), .s(sm));

    // dff for 4bit sum
    dff Ds0(.Q(s[0]), .D(sm[0]), .clk(clk));
    dff Ds1(.Q(s[1]), .D(sm[1]), .clk(clk));
    dff Ds2(.Q(s[2]), .D(sm[2]), .clk(clk));
    dff Ds3(.Q(s[3]), .D(sm[3]), .clk(clk));

    // dff for cout
    dff Dcout(.Q(cout), .D(coutm), .clk(clk));
endmodule

module dff(Q, D, clk);
    input clk, D;
    output reg Q;
    always@(posedge clk)
    begin
            Q <= D;
    end
endmodule



module cla(a, b, cin, cout, s);
    input [3:0] a, b;
    input cin;     
    output [3:0] s;
    output cout; 

    wire p0, p1, p2, p3;
    wire g0, g1, g2, g3;
    wire c1, c2, c3;
    wire c11, c21, c22, c31, c32, c33, c41, c42, c43, c44; 
    

   // propgen
    xor Xprop0(p0, a[0], b[0]);
    xor Xprop1(p1, a[1], b[1]);
    xor Xprop2(p2, a[2], b[2]);
    xor Xprop3(p3, a[3], b[3]);

    and Xgen0(g0, a[0], b[0]);
    and Xgen1(g1, a[1], b[1]);
    and Xgen2(g2, a[2], b[2]);
    and Xgen3(g3, a[3], b[3]);


    // carry
    and Xc11(c11, p0, cin);
    or Xco11(c1, g0, c11);

    and Xc21(c21, p1, p0, cin);
    and Xc22(c22, p1, g0);
    or Xco22(c2, c21, c22, g1);
    
    and Xc31(c31, p2, p1, p0, cin);
    and Xc32(c32, p2, p1, g0);
    and Xc33(c33, p2, g1);
    or Xco33(c3, c31, c32, c33, g2);

    and Xc41(c41, p3, p2, p1, p0, cin);
    and Xc42(c42, p3, p2, p1, g0);
    and Xc43(c43, p3, p2, g1);
    and Xc44(c44, p3, g2);
    or Xco44(cout, c41, c42, c43, c44, g3);

    
    // sum
    xor Xsum0(s[0], p0, cin);
    xor Xsum1(s[1], p1, c1);
    xor Xsum2(s[2], p2, c2);
    xor Xsum3(s[3], p3, c3);

endmodule

fpga/full-ckt-tb.v
module full_ckt_tb;
    reg [3:0] a, b;
    reg cin, clk;
    wire cout;
    wire [3:0] s;
    clad uut(
        .a(a), .b(b), .cin(cin),
        .cout(cout), .s(s), .clk(clk)
    );

    initial begin 
        $dumpfile("full_ckt_tb.vcd");
        $dumpvars(0, full_ckt_tb);
        a = 0; b = 0; clk = 0;
        //test cases

        a = 4'b0000; b = 4'b0000; cin = 1'b0;  // test0: 0 + 0 = 0
        a = 4'b0001; b = 4'b0010; cin = 1'b1; #10;  // test1: 1 + 2 + 1 = 4
        a = 4'b0011; b = 4'b0101; cin = 1'b0; #10;  // test2: 1 + 2 = 3
        a = 4'b1010; b = 4'b0101; cin = 1'b0; #10;  // test3: 10 + 5 = 15
        a = 4'b1010; b = 4'b1100; cin = 1'b1; #10;  // test3: 10 + 12 + 1 = 23      **************
        a = 4'b1111; b = 4'b0001; cin = 1'b0; #10;  // test4: 15 + 1 = 16 (carry out)
        a = 4'b1111; b = 4'b1111; cin = 1'b0; #10;  // test4: 15 + 15 = 30 (carry out)
        #50 $finish;
    end
    always #5 clk = ~clk;
endmodule

Verilog/full_ckt_tb.vcd
$date
	Mon Dec  2 20:53:21 2024
$end
$version
	Icarus Verilog
$end
$timescale
	1s
$end
$scope module full_ckt_tb $end
$var wire 4 ! s [3:0] $end
$var wire 1 " cout $end
$var reg 4 # a [3:0] $end
$var reg 4 $ b [3:0] $end
$var reg 1 % cin $end
$var reg 1 & clk $end
$scope module uut $end
$var wire 4 ' a [3:0] $end
$var wire 4 ( b [3:0] $end
$var wire 1 % cin $end
$var wire 1 & clk $end
$var wire 4 ) sm [3:0] $end
$var wire 4 * s [3:0] $end
$var wire 1 + coutm $end
$var wire 1 " cout $end
$var wire 1 , cinm $end
$var wire 4 - bm [3:0] $end
$var wire 4 . am [3:0] $end
$scope module C1 $end
$var wire 4 / a [3:0] $end
$var wire 4 0 b [3:0] $end
$var wire 1 1 c1 $end
$var wire 1 2 c11 $end
$var wire 1 3 c2 $end
$var wire 1 4 c21 $end
$var wire 1 5 c22 $end
$var wire 1 6 c3 $end
$var wire 1 7 c31 $end
$var wire 1 8 c32 $end
$var wire 1 9 c33 $end
$var wire 1 : c41 $end
$var wire 1 ; c42 $end
$var wire 1 < c43 $end
$var wire 1 = c44 $end
$var wire 1 + cout $end
$var wire 1 > g0 $end
$var wire 1 ? g1 $end
$var wire 1 @ g2 $end
$var wire 1 A g3 $end
$var wire 1 B p0 $end
$var wire 1 C p1 $end
$var wire 1 D p2 $end
$var wire 1 E p3 $end
$var wire 4 F s [3:0] $end
$var wire 1 , cin $end
$upscope $end
$scope module Da0 $end
$var wire 1 G D $end
$var wire 1 & clk $end
$var reg 1 H Q $end
$upscope $end
$scope module Da1 $end
$var wire 1 I D $end
$var wire 1 & clk $end
$var reg 1 J Q $end
$upscope $end
$scope module Da2 $end
$var wire 1 K D $end
$var wire 1 & clk $end
$var reg 1 L Q $end
$upscope $end
$scope module Da3 $end
$var wire 1 M D $end
$var wire 1 & clk $end
$var reg 1 N Q $end
$upscope $end
$scope module Db0 $end
$var wire 1 O D $end
$var wire 1 & clk $end
$var reg 1 P Q $end
$upscope $end
$scope module Db1 $end
$var wire 1 Q D $end
$var wire 1 & clk $end
$var reg 1 R Q $end
$upscope $end
$scope module Db2 $end
$var wire 1 S D $end
$var wire 1 & clk $end
$var reg 1 T Q $end
$upscope $end
$scope module Db3 $end
$var wire 1 U D $end
$var wire 1 & clk $end
$var reg 1 V Q $end
$upscope $end
$scope module Dcin $end
$var wire 1 % D $end
$var wire 1 & clk $end
$var reg 1 , Q $end
$upscope $end
$scope module Dcout $end
$var wire 1 + D $end
$var wire 1 & clk $end
$var reg 1 " Q $end
$upscope $end
$scope module Ds0 $end
$var wire 1 W D $end
$var wire 1 & clk $end
$var reg 1 X Q $end
$upscope $end
$scope module Ds1 $end
$var wire 1 Y D $end
$var wire 1 & clk $end
$var reg 1 Z Q $end
$upscope $end
$scope module Ds2 $end
$var wire 1 [ D $end
$var wire 1 & clk $end
$var reg 1 \ Q $end
$upscope $end
$scope module Ds3 $end
$var wire 1 ] D $end
$var wire 1 & clk $end
$var reg 1 ^ Q $end
$upscope $end
$upscope $end
$upscope $end
$enddefinitions $end
$comment Show the parameter values. $end
$dumpall
$end
#0
$dumpvars
x^
x]
x\
x[
xZ
xY
xX
xW
xV
0U
xT
0S
xR
1Q
xP
0O
xN
0M
xL
0K
xJ
0I
xH
1G
bx F
xE
xD
xC
xB
xA
x@
x?
x>
x=
x<
x;
x:
x9
x8
x7
x6
x5
x4
x3
x2
x1
bx 0
bx /
bx .
bx -
x,
x+
bx *
bx )
b10 (
b1 '
0&
1%
b10 $
b1 #
x"
bx !
$end
#5
0Y
1[
0]
0+
11
0W
13
06
0:
12
b100 )
b100 F
14
05
07
08
09
0;
0<
0=
1B
0>
1C
0?
0D
0@
0E
0A
1H
0J
0L
b1 .
b1 /
0N
0P
1R
0T
b10 -
b10 0
0V
1,
1&
#10
1O
0Q
1S
1I
0&
0%
b101 $
b101 (
b11 #
b11 '
#15
0[
1]
16
15
18
0W
13
1D
0B
1>
b1000 )
b1000 F
04
02
0"
0^
1\
0Z
b100 !
b100 *
0X
0,
1T
0R
b101 -
b101 0
1P
b11 .
b11 /
1J
1&
#20
0G
1M
0&
b1010 #
b1010 '
#25
1[
1Y
1W
03
06
1]
01
05
08
b1111 )
b1111 F
1B
0>
1E
0H
b1010 .
b1010 /
1N
0\
b1000 !
b1000 *
1^
1&
#30
0O
1U
0&
1%
b1100 $
b1100 (
#35
0]
1[
1Y
1+
1W
0:
06
03
01
0E
1A
0B
b111 )
b111 F
07
04
02
1\
1Z
b1111 !
b1111 *
1X
1,
1V
b1100 -
b1100 0
0P
1&
#40
1O
0S
0U
1G
1K
0&
0%
b1 $
b1 (
b1111 #
b1111 '
#45
0[
0Y
13
16
0]
1+
11
15
18
1;
1>
1E
0A
0W
b0 )
b0 F
1H
b1111 .
b1111 /
1L
1P
0T
b1 -
b1 0
0V
0,
b111 !
b111 *
0^
1"
1&
#50
1Q
1S
1U
0&
b1111 $
b1111 (
#55
1]
1[
1Y
05
08
0;
b1110 )
b1110 F
0E
1A
0D
1@
0C
1?
0\
0Z
b0 !
b0 *
0X
1V
1T
b1111 -
b1111 0
1R
1&
#60
0&
#65
1Z
1\
b1110 !
b1110 *
1^
1&
